setup.cfg
setup.py
hichao_thrift.egg-info/PKG-INFO
hichao_thrift.egg-info/SOURCES.txt
hichao_thrift.egg-info/dependency_links.txt
hichao_thrift.egg-info/top_level.txt
src/TSCons.py
src/TSerialization.py
src/TTornado.py
src/Thrift.py
src/__init__.py
src/protocol/TBase.py
src/protocol/TBinaryProtocol.py
src/protocol/TCompactProtocol.py
src/protocol/TJSONProtocol.py
src/protocol/TProtocol.py
src/protocol/__init__.py
src/protocol/fastbinary.c
src/server/THttpServer.py
src/server/TNonblockingServer.py
src/server/TProcessPoolServer.py
src/server/TServer.py
src/server/__init__.py
src/transport/THttpClient.py
src/transport/TSSLSocket.py
src/transport/TSocket.py
src/transport/TTransport.py
src/transport/TTwisted.py
src/transport/TZlibTransport.py
src/transport/__init__.py