Metadata-Version: 1.1
Name: hichao-thrift
Version: 1.0.0
Summary: Python bindings for the Apache Thrift RPC system
Home-page: http://thrift.apache.org
Author: ['Thrift Developers']
Author-email: ['dev@thrift.apache.org']
License: Apache License 2.0
Platform: UNKNOWN
Classifier: Development Status :: 5 - Production/Stable
Classifier: Environment :: Console
Classifier: Intended Audience :: Developers
Classifier: Programming Language :: Python
Classifier: Programming Language :: Python :: 2
Classifier: Topic :: Software Development :: Libraries
Classifier: Topic :: System :: Networking
